distributions_vul3rmp/Binomialdistribution.py
distributions_vul3rmp/Gaussiandistribution.py
distributions_vul3rmp/Generaldistribution.py
distributions_vul3rmp/__init__.py
distributions_vul3rmp-0.1.dist-info/METADATA
distributions_vul3rmp-0.1.dist-info/WHEEL
distributions_vul3rmp-0.1.dist-info/top_level.txt
distributions_vul3rmp-0.1.dist-info/RECORD
