Metadata-Version: 2.1
Name: distributions-vul3rmp
Version: 0.1
Summary: Gaussian distributions
Home-page: UNKNOWN
Author: Hsiao-Chun Hu
Author-email: hsiaochun.hu@outlook.com
License: UNKNOWN
Platform: UNKNOWN
